gymnasium_search_race/__init__.py
gymnasium_search_race/envs/__init__.py
gymnasium_search_race/envs/mad_pod_racing.py
gymnasium_search_race/envs/models.py
gymnasium_search_race/envs/search_race.py
gymnasium_search_race/envs/assets/mad_pod_racing/background.jpg
gymnasium_search_race/envs/assets/mad_pod_racing/space_ship_blocker.png
gymnasium_search_race/envs/assets/mad_pod_racing/space_ship_runner.png
gymnasium_search_race/envs/assets/search_race/back.jpg
gymnasium_search_race/envs/assets/search_race/car.png
gymnasium_search_race/envs/maps/test1.json
gymnasium_search_race/envs/maps/test10.json
gymnasium_search_race/envs/maps/test11.json
gymnasium_search_race/envs/maps/test12.json
gymnasium_search_race/envs/maps/test13.json
gymnasium_search_race/envs/maps/test14.json
gymnasium_search_race/envs/maps/test15.json
gymnasium_search_race/envs/maps/test16.json
gymnasium_search_race/envs/maps/test17.json
gymnasium_search_race/envs/maps/test18.json
gymnasium_search_race/envs/maps/test19.json
gymnasium_search_race/envs/maps/test2.json
gymnasium_search_race/envs/maps/test20.json
gymnasium_search_race/envs/maps/test21.json
gymnasium_search_race/envs/maps/test22.json
gymnasium_search_race/envs/maps/test23.json
gymnasium_search_race/envs/maps/test24.json
gymnasium_search_race/envs/maps/test25.json
gymnasium_search_race/envs/maps/test26.json
gymnasium_search_race/envs/maps/test27.json
gymnasium_search_race/envs/maps/test28.json
gymnasium_search_race/envs/maps/test29.json
gymnasium_search_race/envs/maps/test30.json
gymnasium_search_race/envs/maps/test31.json
gymnasium_search_race/envs/maps/test32.json
gymnasium_search_race/envs/maps/test33.json
gymnasium_search_race/envs/maps/test34.json
gymnasium_search_race/envs/maps/test35.json
gymnasium_search_race/envs/maps/test36.json
gymnasium_search_race/envs/maps/test37.json
gymnasium_search_race/envs/maps/test38.json
gymnasium_search_race/envs/maps/test39.json
gymnasium_search_race/envs/maps/test40.json
gymnasium_search_race-4.1.0.dist-info/licenses/LICENSE
gymnasium_search_race-4.1.0.dist-info/METADATA
gymnasium_search_race-4.1.0.dist-info/WHEEL
gymnasium_search_race-4.1.0.dist-info/top_level.txt
gymnasium_search_race-4.1.0.dist-info/RECORD
