Metadata-Version: 2.4
Name: gymnasium_search_race
Version: 4.1.0
Summary: A reinforcement learning environment for the Search Race CG puzzle based on Gymnasium
Author-email: Quentin Deschamps <quentindeschamps18@gmail.com>
License: MIT
Project-URL: Repository, https://github.com/Quentin18/gymnasium-search-race
Keywords: Reinforcement Learning,game,RL,AI,gymnasium,pygame
Classifier: License :: OSI Approved :: MIT License
Classifier: Programming Language :: Python :: 3
Classifier: Programming Language :: Python :: 3.10
Classifier: Programming Language :: Python :: 3.11
Classifier: Programming Language :: Python :: 3.12
Classifier: Topic :: Games/Entertainment
Classifier: Topic :: Scientific/Engineering :: Artificial Intelligence
Requires-Python: >=3.10
License-File: LICENSE
Requires-Dist: gymnasium==1.2.0
Requires-Dist: pygame==2.6.1
Requires-Dist: stable-baselines3==2.7.0
Provides-Extra: training
Requires-Dist: moviepy==2.2.1; extra == "training"
Requires-Dist: rl_zoo3==2.7.0; extra == "training"
Requires-Dist: tensorboard==2.20.0; extra == "training"
Provides-Extra: testing
Requires-Dist: pytest; extra == "testing"
Provides-Extra: quality
Requires-Dist: black[d]; extra == "quality"
Requires-Dist: isort; extra == "quality"
Requires-Dist: pylint; extra == "quality"
Dynamic: license-file
